README.md
setup.cfg
setup.py
TikTokApi/__init__.py
TikTokApi/browser.py
TikTokApi/get_acrawler.py
TikTokApi/stealth.py
TikTokApi/tiktok.py
TikTokApi/tiktokuser.py
TikTokApi/utilities.py
TikTokApi_Pyppeteer.egg-info/PKG-INFO
TikTokApi_Pyppeteer.egg-info/SOURCES.txt
TikTokApi_Pyppeteer.egg-info/dependency_links.txt
TikTokApi_Pyppeteer.egg-info/requires.txt
TikTokApi_Pyppeteer.egg-info/top_level.txt