Metadata-Version: 2.1
Name: TikTokApi-Pyppeteer
Version: 3.7.9
Summary: The Unofficial TikTok API Wrapper But Pyppeteer in Python 3.
Home-page: https://github.com/davidteather/tiktok-api
Author: David Teather
Author-email: contact.davidteather@gmail.com
License: MIT
Download-URL: https://github.com/davidteather/TikTok-Api/tarball/pyppeteer
Keywords: tiktok,python3,api,unofficial,tiktok-api,tiktok api
Platform: UNKNOWN
Classifier: Development Status :: 3 - Alpha
Classifier: Intended Audience :: Developers
Classifier: Topic :: Software Development :: Build Tools
Classifier: License :: OSI Approved :: MIT License
Classifier: Programming Language :: Python :: 3.6
Classifier: Programming Language :: Python :: 3.7
Classifier: Programming Language :: Python :: 3.8
Classifier: Programming Language :: Python :: 3.9
